vsdx_rdf/__init__.py
vsdx_rdf/_modidx.py
vsdx_rdf/core.py
vsdx_rdf/visualize.py
vsdx_rdf-0.0.1.dist-info/LICENSE
vsdx_rdf-0.0.1.dist-info/METADATA
vsdx_rdf-0.0.1.dist-info/WHEEL
vsdx_rdf-0.0.1.dist-info/entry_points.txt
vsdx_rdf-0.0.1.dist-info/top_level.txt
vsdx_rdf-0.0.1.dist-info/RECORD
